{
  "GeofenceList": [
    {
      "droneCount": 1,
      "name": "Scenario 1",
      "isGeofenceFav": false,
      "coordinates": [
        [
          {
            "type": "polygon",
            "waypoints": [
              {
                "lat": 41.27642582647183,
                "lon": 1.9882690180072302
              },
              {
                "lat": 41.276209130231905,
                "lon": 1.9883816707858557
              },
              {
                "lat": 41.27640466082428,
                "lon": 1.9891101792703978
              },
              {
                "lat": 41.27660523025634,
                "lon": 1.988990820969235
              }
            ]
          },
          {
            "type": "polygon",
            "waypoints": [
              {
                "lat": 41.27639357405378,
                "lon": 1.9884007568747677
              },
              {
                "lat": 41.276280690465114,
                "lon": 1.9884624476821102
              },
              {
                "lat": 41.27632906916988,
                "lon": 1.9886005814463772
              },
              {
                "lat": 41.2764409447873,
                "lon": 1.9885268206984676
              }
            ]
          }
        ]
      ]
    }
  ]
}